apk_parse-1.0.0.dist-info/METADATA
apk_parse-1.0.0.dist-info/RECORD
apk_parse-1.0.0.dist-info/WHEEL
apk_parse-1.0.0.dist-info/top_level.txt
main/__init__.py
main/androconf.py
main/apk.py
main/bytecode.py
main/dvm_permissions.py
main/test.py
main/util.py
main/zipfile.py
