Metadata-Version: 2.1
Name: apk-parse
Version: 1.0.0
Summary: parse the Apk file AndroidManifest.xml
Home-page: https://github.com/candledragle/apk_parse.git
Author: candledragle
Author-email: s_abcabc@126.com
License: MIT
Platform: UNKNOWN
Classifier: License :: OSI Approved :: MIT License
Classifier: Programming Language :: Python
Classifier: Programming Language :: Python :: 3
Classifier: Programming Language :: Python :: 3.6
Classifier: Programming Language :: Python :: Implementation :: CPython
Classifier: Programming Language :: Python :: Implementation :: PyPy
Requires-Python: >=2.7
